infraninja/__init__.py
infraninja/netdata.py
infraninja/deploys/ssh_keys/__init__.py
infraninja/deploys/ssh_keys/defaults.py
infraninja/deploys/ssh_keys/util.py
infraninja/deploys/update_and_upgrade/__init__.py
infraninja/deploys/update_and_upgrade/update_and_upgrade.py
infraninja/inventory/coolify.py
infraninja/inventory/jinn.py
infraninja/security/alpine/clamav_setup.py
infraninja/security/alpine/fail2ban_setup.py
infraninja/security/alpine/install_tools.py
infraninja/security/alpine/iptables_setup.py
infraninja/security/alpine/lynis_setup.py
infraninja/security/alpine/suricata_setup.py
infraninja/security/common/__init__.py
infraninja/security/common/acl.py
infraninja/security/common/arp_poisoning_protection.py
infraninja/security/common/auditd_setup.py
infraninja/security/common/chkrootkit_setup.py
infraninja/security/common/common_install.py
infraninja/security/common/disable_services.py
infraninja/security/common/fail2ban_setup.py
infraninja/security/common/iptables_setup.py
infraninja/security/common/kernel_hardening.py
infraninja/security/common/media_autorun.py
infraninja/security/common/nftables_setup.py
infraninja/security/common/reboot_system.py
infraninja/security/common/smtp_hardening.py
infraninja/security/common/ssh_hardening.py
infraninja/security/common/update_packages.py
infraninja/security/common/UAE_IA_COMPLIANCE/T3.6.3.py
infraninja/security/freebsd/__init__.py
infraninja/security/freebsd/acl.py
infraninja/security/freebsd/bsm_setup.py
infraninja/security/freebsd/chkrootkit_setup.py
infraninja/security/freebsd/disable_services.py
infraninja/security/freebsd/fail2ban_setup.py
infraninja/security/freebsd/install_tools.py
infraninja/security/freebsd/lynis_setup.py
infraninja/security/freebsd/pf_setup.py
infraninja/security/freebsd/rkhunter_setup.py
infraninja/security/freebsd/ssh_hardening.py
infraninja/security/freebsd/update_packages.py
infraninja/security/patches/__init__.py
infraninja/security/patches/ntp_security_patch.py
infraninja-0.3.0.dist-info/licenses/LICENSE
infraninja-0.3.0.dist-info/METADATA
infraninja-0.3.0.dist-info/WHEEL
infraninja-0.3.0.dist-info/top_level.txt
infraninja-0.3.0.dist-info/RECORD
