Metadata-Version: 2.4
Name: infraninja
Version: 0.3.0
Summary: ninja-level deployments designed to simplify infrastructure management and automate common tasks
Author-email: Mohammad Abu-khader <mohammad@kalvad.com>
License: MIT License
Project-URL: Homepage, https://github.com/KalvadTech/infraninja
Project-URL: Issues, https://github.com/KalvadTech/infraninja/issues
Classifier: Programming Language :: Python :: 3
Classifier: Operating System :: OS Independent
Requires-Python: >=3.8
License-File: LICENSE
Requires-Dist: pyinfra
Requires-Dist: requests
Dynamic: license-file
